ibm_cpp_orchestration/__init__.py
ibm_cpp_orchestration/client.py
ibm_cpp_orchestration/client_errors.py
ibm_cpp_orchestration/cpd_paths.py
ibm_cpp_orchestration/utils.py
ibm_cpp_orchestration/version.py
ibm_cpp_orchestration-0.1.0.dist-info/LICENSE
ibm_cpp_orchestration-0.1.0.dist-info/METADATA
ibm_cpp_orchestration-0.1.0.dist-info/WHEEL
ibm_cpp_orchestration-0.1.0.dist-info/top_level.txt
ibm_cpp_orchestration-0.1.0.dist-info/RECORD
