Metadata-Version: 2.1
Name: ibm-cpp-orchestration
Version: 0.1.0
Summary: Supports users in usage of CPD Orchestration
Home-page: https://github.ibm.com/AILifecycle/ibm-cpp-orchestration
Author: Michalina Kotwica
Author-email: michalina.kotwica@ibm.com
License: UNKNOWN
Platform: UNKNOWN
Classifier: Programming Language :: Python :: 3
Classifier: License :: OSI Approved :: MIT License
Classifier: Operating System :: OS Independent
Requires-Python: >=3.7
Requires-Dist: ibm-cloud-sdk-core (>=3.3.2)
Requires-Dist: ibm-cos-sdk (>=2.8.0)
Requires-Dist: attrs (>=20.3.0)
Requires-Dist: requests (>=2.25.0)
Requires-Dist: responses (>=0.12.1)
